<?xml version="1.0" encoding="utf-8" ?>
<dwsync>
<file name="android-icon-144x144.png" server="ftp.360criativo.com.br" local="134254157899068651" remote="134085132000000000" Dst="0" />
<file name="android-icon-192x192.png" server="ftp.360criativo.com.br" local="134254159579037836" remote="134085132000000000" Dst="0" />
<file name="android-icon-36x36.png" server="ftp.360criativo.com.br" local="134254157919434159" remote="134085132000000000" Dst="0" />
<file name="android-icon-48x48.png" server="ftp.360criativo.com.br" local="134254157932064776" remote="134085132000000000" Dst="0" />
<file name="android-icon-72x72.png" server="ftp.360criativo.com.br" local="134254157945372483" remote="134085132000000000" Dst="0" />
<file name="apple-icon-114x114.png" server="ftp.360criativo.com.br" local="134254159531655380" remote="134085132000000000" Dst="0" />
<file name="android-icon-96x96.png" server="ftp.360criativo.com.br" local="134254157959654556" remote="134085132000000000" Dst="0" />
<file name="apple-icon-120x120.png" server="ftp.360criativo.com.br" local="134254159537346125" remote="134085132000000000" Dst="0" />
<file name="apple-icon-144x144.png" server="ftp.360criativo.com.br" local="134254159657963115" remote="134085132000000000" Dst="0" />
<file name="apple-icon-180x180.png" server="ftp.360criativo.com.br" local="134254159556425501" remote="134085132000000000" Dst="0" />
<file name="apple-icon-57x57.png" server="ftp.360criativo.com.br" local="134254159510647286" remote="134085132000000000" Dst="0" />
<file name="apple-icon-152x152.png" server="ftp.360criativo.com.br" local="134254159543100916" remote="134085132000000000" Dst="0" />
<file name="apple-icon-60x60.png" server="ftp.360criativo.com.br" local="134254159512983493" remote="134085132000000000" Dst="0" />
<file name="apple-icon-72x72.png" server="ftp.360criativo.com.br" local="134254159524557722" remote="134085132000000000" Dst="0" />
<file name="apple-icon-precomposed.png" server="ftp.360criativo.com.br" local="134254158032811806" remote="134085132000000000" Dst="0" />
<file name="apple-icon-76x76.png" server="ftp.360criativo.com.br" local="134254159518865029" remote="134085132000000000" Dst="0" />
<file name="apple-icon.png" server="ftp.360criativo.com.br" local="134254158042441241" remote="134085132000000000" Dst="0" />
<file name="browserconfig.xml" server="ftp.360criativo.com.br" local="134254158045897343" remote="134085132000000000" Dst="0" />
<file name="favicon-32x32.png" server="ftp.360criativo.com.br" local="134254159584812363" remote="134085132000000000" Dst="0" />
<file name="favicon-16x16.png" server="ftp.360criativo.com.br" local="134254159618412961" remote="134085132000000000" Dst="0" />
<file name="favicon.ico" server="ftp.360criativo.com.br" local="134254158067601588" remote="134085132000000000" Dst="0" />
<file name="manifest.json" server="ftp.360criativo.com.br" local="134254159626679348" remote="134085132000000000" Dst="0" />
<file name="favicon-96x96.png" server="ftp.360criativo.com.br" local="134254159612588461" remote="134085132000000000" Dst="0" />
<file name="ms-icon-144x144.png" server="ftp.360criativo.com.br" local="134254158093221791" remote="134085132000000000" Dst="0" />
<file name="ms-icon-70x70.png" server="ftp.360criativo.com.br" local="134254158099059131" remote="134085132000000000" Dst="0" />
<file name="ms-icon-150x150.png" server="ftp.360criativo.com.br" local="134254158102646826" remote="134085132000000000" Dst="0" />
<file name="ms-icon-310x310.png" server="ftp.360criativo.com.br" local="134254158106013592" remote="134085132000000000" Dst="0" />
</dwsync>